{
  "swagger_path": "specifications/read-write/v3.1.1/callback-urls-swagger.yaml",
  "endpoints": [
    {
      "conditionalProperties": [
        "Errors[*].Path",
        "Errors[*].Url",
        "Id",
        "Message",
        "Code"
      ],
      "method": "PUT",
      "path": "/callback-urls/{CallbackUrlId}",
      "status_code": 500
    },
    {
      "conditionalProperties": [
        "Links.First",
        "Links.Last",
        "Links.Next",
        "Links.Prev",
        "Meta.FirstAvailableDateTime",
        "Meta.LastAvailableDateTime",
        "Meta.TotalPages"
      ],
      "method": "PUT",
      "path": "/callback-urls/{CallbackUrlId}",
      "status_code": 200
    },
    {
      "conditionalProperties": [
        "Code",
        "Errors[*].Path",
        "Errors[*].Url",
        "Id",
        "Message"
      ],
      "method": "PUT",
      "path": "/callback-urls/{CallbackUrlId}",
      "status_code": 400
    },
    {
      "conditionalProperties": [
        "Id",
        "Message",
        "Code",
        "Errors[*].Path",
        "Errors[*].Url"
      ],
      "method": "DELETE",
      "path": "/callback-urls/{CallbackUrlId}",
      "status_code": 500
    },
    {
      "conditionalProperties": [
        "Code",
        "Errors[*].Path",
        "Errors[*].Url",
        "Id",
        "Message"
      ],
      "method": "DELETE",
      "path": "/callback-urls/{CallbackUrlId}",
      "status_code": 400
    },
    {
      "conditionalProperties": [
        "Code",
        "Errors[*].Path",
        "Errors[*].Url",
        "Id",
        "Message"
      ],
      "method": "GET",
      "path": "/callback-urls",
      "status_code": 500
    },
    {
      "conditionalProperties": [
        "Links.First",
        "Links.Last",
        "Links.Next",
        "Links.Prev",
        "Meta.FirstAvailableDateTime",
        "Meta.LastAvailableDateTime",
        "Meta.TotalPages"
      ],
      "method": "GET",
      "path": "/callback-urls",
      "status_code": 200
    },
    {
      "conditionalProperties": [
        "Code",
        "Errors[*].Path",
        "Errors[*].Url",
        "Id",
        "Message"
      ],
      "method": "GET",
      "path": "/callback-urls",
      "status_code": 400
    },
    {
      "conditionalProperties": [
        "Code",
        "Errors[*].Path",
        "Errors[*].Url",
        "Id",
        "Message"
      ],
      "method": "POST",
      "path": "/callback-urls",
      "status_code": 500
    },
    {
      "conditionalProperties": [
        "Links.Last",
        "Links.Next",
        "Links.Prev",
        "Links.First",
        "Meta.FirstAvailableDateTime",
        "Meta.LastAvailableDateTime",
        "Meta.TotalPages"
      ],
      "method": "POST",
      "path": "/callback-urls",
      "status_code": 201
    },
    {
      "conditionalProperties": [
        "Code",
        "Errors[*].Path",
        "Errors[*].Url",
        "Id",
        "Message"
      ],
      "method": "POST",
      "path": "/callback-urls",
      "status_code": 400
    }
  ]
}